LICENSE
MANIFEST.in
README.md
setup.py
libpytools_fm/__init__.py
libpytools_fm/github_api.py
libpytools_fm.egg-info/PKG-INFO
libpytools_fm.egg-info/SOURCES.txt
libpytools_fm.egg-info/dependency_links.txt
libpytools_fm.egg-info/not-zip-safe
libpytools_fm.egg-info/requires.txt
libpytools_fm.egg-info/top_level.txt