Metadata-Version: 2.1
Name: libpytools-fm
Version: 0.2
Summary: Módulo para exemplificar a construção de projetos Python
Home-page: https://github.com/FerreiraMa/libpytools
Author: Marcelo Ferreira
Author-email: ferreirasantos1976@uol.com.br
License: GNU AFFERO GENERAL PUBLIC LICENSE
Platform: UNKNOWN
Classifier: Development Status :: 2 - Pre-Alpha
Classifier: Environment :: Console
Classifier: Intended Audience :: Developers
Classifier: License :: OSI Approved :: GNU Affero General Public License v3 or later (AGPLv3+)
Classifier: Operating System :: OS Independent
Classifier: Programming Language :: Python
Classifier: Programming Language :: Python :: 3.9
Classifier: Framework :: Pytest
